grdpcli/__init__.py
grdpcli/cmd_copy.py
grdpcli/cmd_exec.py
grdpcli/help_content.py
grdpcli/variables.py
grdpcli/version.py
grdpcli-2.1.7.data/data/__init__.py
grdpcli-2.1.7.data/data/cmd_copy.py
grdpcli-2.1.7.data/data/cmd_exec.py
grdpcli-2.1.7.data/data/help_content.py
grdpcli-2.1.7.data/data/variables.py
grdpcli-2.1.7.data/data/version.py
grdpcli-2.1.7.data/data/share/grdpcli/grdpcli/.version
grdpcli-2.1.7.data/data/share/grdpcli/grdpcli/__init__.py
grdpcli-2.1.7.data/data/share/grdpcli/grdpcli/cmd_copy.py
grdpcli-2.1.7.data/data/share/grdpcli/grdpcli/cmd_exec.py
grdpcli-2.1.7.data/data/share/grdpcli/grdpcli/help_content.py
grdpcli-2.1.7.data/data/share/grdpcli/grdpcli/variables.py
grdpcli-2.1.7.data/data/share/grdpcli/grdpcli/version.py
grdpcli-2.1.7.data/scripts/grdp
grdpcli-2.1.7.dist-info/METADATA
grdpcli-2.1.7.dist-info/WHEEL
grdpcli-2.1.7.dist-info/top_level.txt
grdpcli-2.1.7.dist-info/RECORD
