Metadata-Version: 2.4
Name: grdpcli
Version: 2.1.7
Summary: Gitlab Rapid Development Platform CLI client
Home-page: https://onix-systems.com
Author: Anton Marusenko
Author-email: anton.marusenko@onix-systems.com
Requires-Python: >=3
Requires-Dist: GitPython==3.1.24
Requires-Dist: requests==2.27.1
Requires-Dist: tabulate==0.9.0
Requires-Dist: grdp-cli-kubernetes==1.0.2
Requires-Dist: rich==10.16.2
Requires-Dist: questionary==2.0.1
Dynamic: author
Dynamic: author-email
Dynamic: home-page
Dynamic: requires-dist
Dynamic: requires-python
Dynamic: summary
